iot_mcp_server/__init__.py
iot_mcp_server/__main__.py
iot_mcp_server/server.py
iot_mcp_server/test.py
iot_mcp_server/util.py
iot_mcp_server-0.3.1.dist-info/METADATA
iot_mcp_server-0.3.1.dist-info/WHEEL
iot_mcp_server-0.3.1.dist-info/entry_points.txt
iot_mcp_server-0.3.1.dist-info/RECORD
