Metadata-Version: 2.4
Name: iot-mcp-server
Version: 0.3.1
Summary: MCP server for IoT Cloud
Author-email: Johnson Lau <gatement@gmail.com>
Requires-Python: >=3.12
Requires-Dist: mcp[cli]>=1.9.0
Requires-Dist: pyjwt>=2.10.1
Requires-Dist: requests>=2.32.3
